asyncx/__init__.py
asyncx/_version.py
asyncx/context.py
asyncx/coroutine.py
asyncx/event_loop.py
asyncx/py.typed
asyncx/shield.py
asyncx/thread.py
asyncx-0.0.3.dist-info/LICENSE
asyncx-0.0.3.dist-info/METADATA
asyncx-0.0.3.dist-info/WHEEL
asyncx-0.0.3.dist-info/top_level.txt
asyncx-0.0.3.dist-info/RECORD
